odoo/addons/base_cron_exclusion/README.rst
odoo/addons/base_cron_exclusion/__init__.py
odoo/addons/base_cron_exclusion/__manifest__.py
odoo/addons/base_cron_exclusion/i18n/cs_CZ.po
odoo/addons/base_cron_exclusion/i18n/es.po
odoo/addons/base_cron_exclusion/i18n/fr.po
odoo/addons/base_cron_exclusion/models/__init__.py
odoo/addons/base_cron_exclusion/models/ir_cron.py
odoo/addons/base_cron_exclusion/static/description/icon.png
odoo/addons/base_cron_exclusion/views/ir_cron_view.xml
odoo11_addon_base_cron_exclusion-11.0.1.0.0.dist-info/DESCRIPTION.rst
odoo11_addon_base_cron_exclusion-11.0.1.0.0.dist-info/METADATA
odoo11_addon_base_cron_exclusion-11.0.1.0.0.dist-info/RECORD
odoo11_addon_base_cron_exclusion-11.0.1.0.0.dist-info/WHEEL
odoo11_addon_base_cron_exclusion-11.0.1.0.0.dist-info/metadata.json
odoo11_addon_base_cron_exclusion-11.0.1.0.0.dist-info/top_level.txt
